pyformgen/__init__.py
pyformgen/react_generator.py
pyformgen-0.3.0.dist-info/LICENSE
pyformgen-0.3.0.dist-info/METADATA
pyformgen-0.3.0.dist-info/WHEEL
pyformgen-0.3.0.dist-info/top_level.txt
pyformgen-0.3.0.dist-info/RECORD
