Metadata-Version: 2.1
Name: pyformgen
Version: 0.3.0
Summary: A tool to generate form JSON schemas from prompts
Author: Pradnyesh Bhalekar
Author-email: Pradnyesh Bhalekar <you@example.com>
License: MIT
Project-URL: Homepage, https://github.com/your-username/formgen
Project-URL: Bug Tracker, https://github.com/your-username/formgen/issues
Classifier: Programming Language :: Python :: 3
Classifier: License :: OSI Approved :: MIT License
Classifier: Operating System :: OS Independent
Requires-Python: >=3.6
License-File: LICENSE
